etui/__init__.py
etui-0.2.0.dist-info/LICENSE
etui-0.2.0.dist-info/METADATA
etui-0.2.0.dist-info/WHEEL
etui-0.2.0.dist-info/top_level.txt
etui-0.2.0.dist-info/RECORD
