Metadata-Version: 2.1
Name: etui
Version: 0.2.0
Summary: Exquisite capsule fitted with useful helpers for every day coding.
Home-page: https://github.com/mlueckl/etui
Author: Michael Lueckl
Author-email: mlueckl@pm.me
License: MIT License
License-File: LICENSE
